jupyter_azure/__init__.py
jupyter_azure/_version.py
jupyter_azure/handlers.py
jupyter_azure/tests/__init__.py
jupyter_azure/tests/test_handlers.py
jupyter_azure-0.0.2.data/data/etc/jupyter/jupyter_notebook_config.d/jupyter_azure.json
jupyter_azure-0.0.2.data/data/etc/jupyter/jupyter_server_config.d/jupyter_azure.json
jupyter_azure-0.0.2.data/data/share/jupyter/labextensions/@datalayer/jupyter-azure/build_log.json
jupyter_azure-0.0.2.data/data/share/jupyter/labextensions/@datalayer/jupyter-azure/package.json
jupyter_azure-0.0.2.data/data/share/jupyter/labextensions/@datalayer/jupyter-azure/schemas/@datalayer/jupyter-admin/package.json.orig
jupyter_azure-0.0.2.data/data/share/jupyter/labextensions/@datalayer/jupyter-azure/schemas/@datalayer/jupyter-admin/plugin.json
jupyter_azure-0.0.2.data/data/share/jupyter/labextensions/@datalayer/jupyter-azure/static/lib_index_js.4348b810ae8dc12e002f.js
jupyter_azure-0.0.2.data/data/share/jupyter/labextensions/@datalayer/jupyter-azure/static/lib_index_js.4348b810ae8dc12e002f.js.map
jupyter_azure-0.0.2.data/data/share/jupyter/labextensions/@datalayer/jupyter-azure/static/remoteEntry.60045aa25abfdbe55e4f.js
jupyter_azure-0.0.2.data/data/share/jupyter/labextensions/@datalayer/jupyter-azure/static/remoteEntry.60045aa25abfdbe55e4f.js.map
jupyter_azure-0.0.2.data/data/share/jupyter/labextensions/@datalayer/jupyter-azure/static/style.js
jupyter_azure-0.0.2.data/data/share/jupyter/labextensions/@datalayer/jupyter-azure/static/style_index_js.09ea6e1de3ce833faf40.js
jupyter_azure-0.0.2.data/data/share/jupyter/labextensions/@datalayer/jupyter-azure/static/style_index_js.09ea6e1de3ce833faf40.js.map
jupyter_azure-0.0.2.data/data/share/jupyter/labextensions/@datalayer/jupyter-azure/static/vendors-node_modules_css-loader_dist_runtime_api_js-node_modules_css-loader_dist_runtime_cssW-72eba1.bac0ab4f283009af8f3d.js
jupyter_azure-0.0.2.dist-info/METADATA
jupyter_azure-0.0.2.dist-info/WHEEL
jupyter_azure-0.0.2.dist-info/licenses/LICENSE
jupyter_azure-0.0.2.dist-info/RECORD
